{
  "weekly_intensity": {
    "grades_6_to_9_average_per_group": {
      "6": {
        "Español": 5,
        "Inglés": 3,
        "Sociales": 3,
        "Naturales": 3,
        "Matemáticas": 3,
        "Artes": 2,
        "Ed Física": 2,
        "Ed Religiosa": 2,
        "Geometría": 2,
        "Informática": 2,
        "Música": 2,
        "Tecnología": 2,
        "Etica": 2,
        "Lec Comp": 2
      },
      "7": {
        "Matemáticas": 4,
        "Español": 3,
        "Inglés": 3,
        "Naturales": 3,
        "Sociales": 3,
        "Artes": 2,
        "Ed Religiosa": 1,
        "Ed Física": 2,
        "Etica": 2,
        "Geometría": 2,
        "Música": 2,
        "Tecnología": 2
      },
      "8": {
        "Inglés": 4,
        "Artes": 3,
        "Español": 3,
        "Naturales": 3,
        "Sociales": 3,
        "Tecnología": 3,
        "Informática": 2,
        "Matemáticas": 2,
        "Ed Física": 2,
        "Etica": 2,
        "Geometría": 1,
        "Música": 1,
        "Ed Religiosa": 1
      },
      "9": {
        "Sociales": 4,
        "Español": 3,
        "Inglés": 2.5,
        "Lec. Crítica": 2,
        "Naturales": 3,
        "Matemáticas": 2,
        "Informática": 2,
        "Tecnología": 2,
        "Ed Física": 1.5,
        "Ed Religiosa": 1,
        "Etica": 1,
        "Música": 1,
        "Emprend.": 0.5
      }
    },
    "grades_10_to_11_by_course": {
      "10": {
        "1001": {
          "Artes": 3,
          "Ciencias Políticas": 2,
          "Cul Recreativa Pre": 2,
          "Cul. Deportiva": 2,
          "Cul. Recreativa": 2,
          "Dllo Humano": 2,
          "Economía": 1.5,
          "Ed Religiosa": 1.5,
          "Español": 4,
          "Estadística": 1.5,
          "Etica": 2,
          "Filosofía": 2,
          "Física": 2,
          "Fun. Pedagógica": 2,
          "Informática": 2,
          "Inglés": 2,
          "Matemáticas": 4,
          "Metodología": 1,
          "Prác Deportiva": 2,
          "SENA": 1.5,
          "SyGestión": 2,
          "Tecnología": 3
        },
        "1002": {
          "Artes": 3,
          "Ciencias Políticas": 2,
          "Diseño Industrial": 2,
          "Economía": 1.5,
          "Ed Religiosa": 1.5,
          "Electrónica": 2,
          "Español": 4,
          "Estadística": 1.5,
          "Etica": 2,
          "Filosofía": 2,
          "Física": 2,
          "Informática": 2,
          "Inglés": 2,
          "Matemáticas": 4,
          "Metodología": 1,
          "Microcontroladores": 2,
          "PLC": 2,
          "Procesos": 2,
          "Program.": 2,
          "Química": 1,
          "SENA": 1.5,
          "Tecnología": 3
        },
        "1003": {
          "Artes": 3,
          "Ciencias Políticas": 2,
          "Economía": 1.5,
          "Ed Religiosa": 1.5,
          "Español": 4,
          "Estadística": 1.5,
          "Etica": 2,
          "Filosofía": 2,
          "Física": 2,
          "Informática": 2,
          "Inglés": 2,
          "Matemáticas": 4,
          "Química": 1,
          "Sociales": 2
        },
        "1004": {
          "Artes": 3,
          "Ciencias Políticas": 2,
          "Contabilidad": 2,
          "Economía": 1.5,
          "Ed Religiosa": 1.5,
          "Español": 4,
          "Etica": 2,
          "Filosofía": 2,
          "Física": 2,
          "Informática": 2,
          "Inglés": 2,
          "Legislación": 2,
          "MaT. Financiera": 2,
          "Matemáticas": 4,
          "Metodología": 1,
          "Publicidad y": 2,
          "Química": 1,
          "SENA": 1.5,
          "Sociales": 2
        }
      },
      "11": {
        "1101": {
          "Cul. Deportiva": 2,
          "Cul. Recreativa": 2,
          "Dllo Humano": 2,
          "Economía": 1.5,
          "Ed Religiosa": 1.5,
          "Español": 4,
          "Estadística": 1.5,
          "Etica": 2,
          "Filosofía": 2,
          "Física": 2,
          "Fun. Pedagógica": 2,
          "Informática": 2,
          "Inglés": 2,
          "Matemáticas": 4,
          "Prác Deportiva": 2,
          "SENA": 1.5,
          "SyGestión": 2
        },
        "1102": {
          "Ciencias Políticas": 2,
          "Control Analógico": 2,
          "Diseño Industrial": 2,
          "Economía": 1.5,
          "Ed Religiosa": 1.5,
          "Español": 4,
          "Estadística": 1.5,
          "Etica": 2,
          "Filosofía": 2,
          "Física": 2,
          "Informática": 2,
          "Inglés": 2,
          "Matemáticas": 4,
          "Metodología": 1,
          "Microcontroladores": 2,
          "Neumática": 2,
          "Procesos": 2,
          "Program.": 2,
          "Química": 1,
          "SENA": 1.5
        },
        "1103": {
          "Artes": 3,
          "Ciencias Políticas": 2,
          "Economía": 1.5,
          "Ed Religiosa": 1.5,
          "Español": 4,
          "Estadística": 2,
          "Etica": 2,
          "Filosofía": 2,
          "Física": 2,
          "Informática": 2,
          "Inglés": 2,
          "Matemáticas": 4,
          "Química": 1,
          "SENA": 1.5
        },
        "1104": {
          "Artes": 3,
          "Ciencias Políticas": 2,
          "Contabilidad": 2,
          "Economía": 1.5,
          "Ed Religiosa": 1.5,
          "Español": 4,
          "Etica": 2,
          "Filosofía": 2,
          "Física": 2,
          "Informática": 2,
          "Inglés": 2,
          "Legislación": 2,
          "MaT. Financiera": 2,
          "Matemáticas": 4,
          "Metodología": 1,
          "Paquete Contable": 2,
          "Publicidad y": 2,
          "Química": 1,
          "SENA": 1.5
        }
      }
    }
  }
}